scQUEST/__init__.py
scQUEST/abnormality.py
scQUEST/classifier.py
scQUEST/data.py
scQUEST/individuality.py
scQUEST/utils.py
scQUEST/dataset/__init__.py
scQUEST/dataset/_utils.py
scQUEST/dataset/datasets.py
ai4scr_scQUEST-0.1.0.dist-info/METADATA
ai4scr_scQUEST-0.1.0.dist-info/WHEEL
ai4scr_scQUEST-0.1.0.dist-info/top_level.txt
ai4scr_scQUEST-0.1.0.dist-info/RECORD
