Metadata-Version: 2.1
Name: ai4scr-scQUEST
Version: 0.1.0
Summary: scQUEST package
Home-page: https://github.ibm.com/art-zurich/scQUEST
Author: Adriano Martinelli, Marianna Rapsomaniki, Johanna Wagner
Author-email: art@zurich.ibm.com
Requires-Dist: pandas (>=1.3)
Requires-Dist: torch (>=1.11)
Requires-Dist: scikit-learn (>=1.0)
Requires-Dist: umap-learn (>=0.5.3)
Requires-Dist: numpy (>=1.2)
Requires-Dist: pytorch-lightning (>=1.6)
Requires-Dist: anndata (>0.7)
Requires-Dist: matplotlib (>=3.5)
Requires-Dist: seaborn (>=0.11)
Requires-Dist: torchmetrics (>=0.7)
Requires-Dist: ipywidgets (>=7.7)
Requires-Dist: protobuf (==3.20.0)
Provides-Extra: dev
Requires-Dist: pytest ; extra == 'dev'
Requires-Dist: pytest-cov ; extra == 'dev'
Requires-Dist: black (==21.5b0) ; extra == 'dev'
Requires-Dist: flake8 ; extra == 'dev'
Requires-Dist: mypy ; extra == 'dev'
Requires-Dist: sphinx ; extra == 'dev'
Requires-Dist: sphinx-autodoc-typehints ; extra == 'dev'
Requires-Dist: better-apidoc ; extra == 'dev'
Requires-Dist: six ; extra == 'dev'
Requires-Dist: sphinx-rtd-theme ; extra == 'dev'
Requires-Dist: myst-parser ; extra == 'dev'
Provides-Extra: test
Requires-Dist: pytest ; extra == 'test'
Requires-Dist: pytest-cov ; extra == 'test'
Provides-Extra: vcs
